cypher_guard-3.0.0.dist-info/METADATA
cypher_guard-3.0.0.dist-info/WHEEL
cypher_guard/__init__.py
cypher_guard/cypher_guard.cpython-312-x86_64-linux-gnu.so
cypher_guard-3.0.0.dist-info/RECORD
