Metadata-Version: 2.4
Name: cypher_guard
Version: 3.0.0
Classifier: Development Status :: 4 - Beta
Classifier: Intended Audience :: Developers
Classifier: License :: OSI Approved :: MIT License
Classifier: Operating System :: OS Independent
Classifier: Programming Language :: Python :: 3
Classifier: Programming Language :: Python :: 3.9
Classifier: Programming Language :: Python :: 3.10
Classifier: Programming Language :: Python :: 3.11
Classifier: Programming Language :: Python :: 3.12
Classifier: Topic :: Database
Classifier: Topic :: Software Development :: Libraries :: Python Modules
Classifier: Topic :: Text Processing :: Linguistic
Summary: Python bindings for Cypher Guard - A Rust library for parsing and validating Cypher queries against a user-defined schema
Keywords: cypher,neo4j,validation,parser,graph,database
Author: Neo4j Field Team
Maintainer: Neo4j Field Team
License: MIT
Requires-Python: >=3.9.0
Project-URL: Homepage, https://github.com/neo4j-field/cypher-guard
Project-URL: Documentation, https://github.com/neo4j-field/cypher-guard#readme
Project-URL: Repository, https://github.com/neo4j-field/cypher-guard
Project-URL: Issues, https://github.com/neo4j-field/cypher-guard/issues
